fastapi_timeout/__init__.py
fastapi_timeout/middleware.py
fastapi_timeout/py.typed
fastapi_timeout-0.1.1.post1.dist-info/licenses/LICENSE
fastapi_timeout-0.1.1.post1.dist-info/METADATA
fastapi_timeout-0.1.1.post1.dist-info/WHEEL
fastapi_timeout-0.1.1.post1.dist-info/top_level.txt
fastapi_timeout-0.1.1.post1.dist-info/RECORD
