Metadata-Version: 2.4
Name: fastapi-timeout
Version: 0.1.1.post1
Summary: Configurable timeout middleware for FastAPI applications
Author-email: Zuhair Abdulla <zuhairamahdi@gmail.com>
License: MIT
Project-URL: Homepage, https://github.com/zuhairamahdi/fastapi-timeout
Project-URL: Documentation, https://github.com/zuhairamahdi/fastapi-timeout#readme
Project-URL: Repository, https://github.com/zuhairamahdi/fastapi-timeout
Project-URL: Bug Tracker, https://github.com/zuhairamahdi/fastapi-timeout/issues
Keywords: fastapi,timeout,middleware,async
Classifier: Development Status :: 4 - Beta
Classifier: Intended Audience :: Developers
Classifier: License :: OSI Approved :: MIT License
Classifier: Operating System :: OS Independent
Classifier: Programming Language :: Python :: 3
Classifier: Programming Language :: Python :: 3.7
Classifier: Programming Language :: Python :: 3.8
Classifier: Programming Language :: Python :: 3.9
Classifier: Programming Language :: Python :: 3.10
Classifier: Programming Language :: Python :: 3.11
Classifier: Programming Language :: Python :: 3.12
Classifier: Topic :: Internet :: WWW/HTTP :: HTTP Servers
Classifier: Topic :: Software Development :: Libraries :: Python Modules
Classifier: Framework :: FastAPI
Requires-Python: >=3.7
License-File: LICENSE
Requires-Dist: fastapi>=0.65.0
Requires-Dist: starlette>=0.14.0
Provides-Extra: dev
Requires-Dist: pytest>=6.0; extra == "dev"
Requires-Dist: pytest-asyncio>=0.21.0; extra == "dev"
Requires-Dist: httpx>=0.23.0; extra == "dev"
Requires-Dist: uvicorn>=0.15.0; extra == "dev"
Dynamic: license-file
Dynamic: requires-python
